dabox_research/__init__.py
dabox_research/env.py
dabox_research/util/__init__.py
dabox_research/util/drawing.py
dabox_research/util/file_io.py
dabox_research-0.2.1.dist-info/LICENSE
dabox_research-0.2.1.dist-info/METADATA
dabox_research-0.2.1.dist-info/WHEEL
dabox_research-0.2.1.dist-info/top_level.txt
dabox_research-0.2.1.dist-info/RECORD
